Trello_Wrapper/__init__.py
Trello_Wrapper/actions/__init__.py
Trello_Wrapper/actions/_delete.py
Trello_Wrapper/actions/_get.py
Trello_Wrapper/actions/_post.py
Trello_Wrapper/actions/_put.py
Trello_Wrapper/boards/__init__.py
Trello_Wrapper/boards/_delete.py
Trello_Wrapper/boards/_get.py
Trello_Wrapper/boards/_post.py
Trello_Wrapper/boards/_put.py
Trello_Wrapper/cards/__init__.py
Trello_Wrapper/cards/_delete.py
Trello_Wrapper/cards/_get.py
Trello_Wrapper/cards/_post.py
Trello_Wrapper/cards/_put.py
Trello_Wrapper/checklists/__init__.py
Trello_Wrapper/checklists/_delete.py
Trello_Wrapper/checklists/_get.py
Trello_Wrapper/checklists/_post.py
Trello_Wrapper/checklists/_put.py
Trello_Wrapper/labels/__init__.py
Trello_Wrapper/labels/_delete.py
Trello_Wrapper/labels/_get.py
Trello_Wrapper/labels/_post.py
Trello_Wrapper/labels/_put.py
Trello_Wrapper/lists/__init__.py
Trello_Wrapper/lists/_delete.py
Trello_Wrapper/lists/_get.py
Trello_Wrapper/lists/_post.py
Trello_Wrapper/lists/_put.py
Trello_Wrapper-0.0.4.dist-info/LICENSE
Trello_Wrapper-0.0.4.dist-info/METADATA
Trello_Wrapper-0.0.4.dist-info/WHEEL
Trello_Wrapper-0.0.4.dist-info/top_level.txt
Trello_Wrapper-0.0.4.dist-info/RECORD
