Metadata-Version: 2.1
Name: Trello-Wrapper
Version: 0.0.4
Summary: A Python Wrapper around the Trello API
Home-page: https://github.com/Rtsil/Trello-Wrapper
Author: Rtsil
Author-email: rtsilavotahina@gmail.com
Keywords: trello,wrapper,api
Classifier: Intended Audience :: Developers
Classifier: License :: OSI Approved :: MIT License
Classifier: Programming Language :: Python :: 3
License-File: LICENSE
Requires-Dist: requests
